blogpack/__init__.py
blogpack/cleaner.py
blogpack/cli.py
blogpack/crawler.py
blogpack/downloader.py
blogpack/linker.py
blogpack/exporters/__init__.py
blogpack/exporters/epub.py
blogpack/exporters/html.py
blogpack/exporters/pdf.py
blogpack/platforms/__init__.py
blogpack/platforms/base.py
blogpack/platforms/ghost.py
blogpack/platforms/substack.py
blogpack/platforms/wordpress.py
blogpack-0.1.1.dist-info/METADATA
blogpack-0.1.1.dist-info/WHEEL
blogpack-0.1.1.dist-info/entry_points.txt
blogpack-0.1.1.dist-info/licenses/LICENSE
blogpack-0.1.1.dist-info/RECORD
