Metadata-Version: 2.4
Name: blogpack
Version: 0.1.1
Summary: Download entire blogs for offline reading with working internal links
Project-URL: Homepage, https://github.com/timf34/blogpack
Project-URL: Repository, https://github.com/timf34/blogpack
Author: Tim Farrelly
License-Expression: GPL-3.0-only
License-File: LICENSE
Keywords: archive,blog,epub,ghost,offline,pdf,substack,wordpress
Classifier: Development Status :: 4 - Beta
Classifier: Environment :: Console
Classifier: Intended Audience :: End Users/Desktop
Classifier: License :: OSI Approved :: GNU General Public License v3 (GPLv3)
Classifier: Operating System :: OS Independent
Classifier: Programming Language :: Python :: 3
Classifier: Programming Language :: Python :: 3.10
Classifier: Programming Language :: Python :: 3.11
Classifier: Programming Language :: Python :: 3.12
Classifier: Topic :: Internet :: WWW/HTTP
Classifier: Topic :: Text Processing :: Markup :: HTML
Requires-Python: >=3.10
Requires-Dist: beautifulsoup4>=4.12.0
Requires-Dist: ebooklib>=0.18
Requires-Dist: httpx>=0.25.0
Requires-Dist: lxml>=4.9.0
Requires-Dist: rich>=13.0.0
Requires-Dist: typer>=0.9.0
Requires-Dist: weasyprint>=60.0
